{
  "name": "Joel Garcia",
  "age": 60,
  "address": {
    "street": "Nakjus Pass",
    "city": "Civese",
    "state": "IA",
    "zip": "61243"
  },
  "contact": {
    "phone": "(783) 209-7832",
    "servicePhone": "800231296"
  },
  "birthday": "2006-10-28T08:36:33.112Z",
  "ip": "4.167.62.59",
  "foo": "bar",
  "profile": {
    "about": "Zujjicvu sofliem zurwamcot im ki mur wozeleh jojokit gen behaaju cet tage du vo welku pafad wag fug. Kurihan uzlip holca ve ikzasdil ipisomut adihij dedhurac sa dufkur tez rilemazo torma ricvo. Kimuzo uf madokisu ob da ru idve fulbin ji dubno op zinsu fa. Ol ravjed gihen linoda uk covaj aceked sop kakigul id nobod wizkin giw uftolref nugucde. Fijo lolwubi vumtidcol ijocevlud uhkok decfi neb zuufohi ivu fo seworosi pohuha jip. Jiaroer jot podhesi ra api vufoh omloj uwsocog obe zupiri ed ekoefawuj nome ungufof.",
    "bio": "Ka me mon tiz pabhubrut vomof nagdeiv ewhaep bijuliv awono jeg ke. Pud mubum ninude pojcebis li cuf imouge bem ubejebba tefo becfopri huza ca udmuvwi pejdefve virpekule jehvijan. Humlevaz monedted hotfi izloeg wazer gugozor he pedtu koc ola vutenojup ikuhiuw olinagza levavuzo wa nuw uku lo."
  },
  "apiKey": "8a1f86f2d118974d5d44dcad80883874d06b48af5b714eae3428cdc24228c749",
  "currency": {
    "code": "USD",
    "name": "United States Dollar"
  }
}